[
   {
    "device_codename": "Xiaomi 11 lite NE 5G (Lisa)",
    "maintainer": "Ankit Kene",
    "rom_support": "https://t.me/ancientid",
    "device_supportgp_url": "https://t.me/ancientofficial_lisa",
    "changelog_url": "https://t.me/ancientrom/1392",
    "date_updated": "14-1-2022",
    "download_url": "https://www.pling.com/p/1606752",
    "phone_url": "https://raw.githubusercontent.com/ancient-devices/ancient_official_devices_gallery/main/xiaomi_mi_11_lite_5g.png"
   },
   {
    "device_codename": "Xiaomi Mi 10T/Pro (apollo)",
    "maintainer": "Maxanderz & Aarunalr",
    "rom_support": "https://t.me/ancientid",
    "device_supportgp_url": "https://t.me/ancientid",
    "changelog_url": "https://t.me/ancientrom/1392",
    "date_updated": "22-1-2022",
    "download_url": "https://www.pling.com/p/1606752",
    "phone_url": " https://fdn2.gsmarena.com/vv/bigpic/xiaomi-mi-10t-5g-pro.jpg"
   },
   {
    "device_codename": "Redmi Note 4(mido)",
    "maintainer": "Smokey",
    "rom_support": "https://t.me/ancientid",
    "device_supportgp_url": "https://t.me/ancientofficialmido",
    "changelog_url": "https://t.me/ancientrom/1392",
    "date_updated": "22-12-2021",
    "download_url": "https://www.pling.com/p/1606752",
    "phone_url": "https://fdn2.gsmarena.com/vv/bigpic/xiaomi-redmi-note-4-sn.jpg"
  },
   {
    "device_codename": "Redmi K20/Mi 9T (davinci)",
    "maintainer": "wadiehabib",
    "rom_support": "https://t.me/ancientid",
    "device_supportgp_url": "https://t.me/wadiehabibroms",
    "changelog_url": "https://telegra.ph/AncientOS-62-01-27",
    "date_updated": "27-01-2022",
    "download_url": "https://www.pling.com/p/1606752",
    "phone_url": "https://fdn2.gsmarena.com/vv/bigpic/xiaomi-mi-9t.jpg"
  },
  {
    "device_codename": "Redmi K20 Pro/Mi 9T Pro (raphael)",
    "maintainer": "wadiehabib",
    "rom_support": "https://t.me/ancientid",
    "device_supportgp_url": "https://t.me/wadiehabibroms",
    "changelog_url": "https://telegra.ph/AncientOS-62-01-27",
    "date_updated": "27-01-2022",
    "download_url": "https://www.pling.com/p/1606752",
    "phone_url": "https://fdn2.gsmarena.com/vv/bigpic/xiaomi-mi-9t.jpg"
  },
  {
    "device_codename": "Redmi 8/8A/8A Dual (olives)",
    "maintainer": "BEERdMANN",
    "rom_support": "https://t.me/ancientid",
    "device_supportgp_url": "https://t.me/ancient_olives",
    "changelog_url": "https://t.me/ancientrom/1394",
    "date_updated": "09-01-2022",
    "download_url": "https://www.pling.com/p/1606752",
    "phone_url": "https://raw.githubusercontent.com/skittels15/banners/main/Redmi-8.jpg"
  },
  {
    "device_codename": "Nokia 6.1 Plus (DRG)",
    "maintainer": "Ankit Kene",
    "rom_support": "https://t.me/ancientid",
    "device_supportgp_url": "https://t.me/ancientPlate2Dragon_Onyx",
    "changelog_url": "https://t.me/ancientrom/1392",
    "date_updated": "04-1-2022",
    "download_url": "https://www.pling.com/p/1606752",
    "phone_url": "https://raw.githubusercontent.com/ancient-devices/ancient_official_devices/main/DRG.png"
  },
  {
    "device_codename": "Nokia 6.1 2018 (PL2)",
    "maintainer": "Ankit Kene",
    "rom_support": "https://t.me/ancientid",
    "device_supportgp_url": "https://t.me/ancientPlate2Dragon_Onyx",
    "changelog_url": "https://t.me/ancientrom/1392",
    "date_updated": "04-1-2022",
    "download_url": "https://www.pling.com/p/1606752",
    "phone_url": "https://fdn2.gsmarena.com/vv/bigpic/nokia-6-2018.jpg"
  },
  {
    "device_codename": "Realme 3/3i",
    "maintainer": "C.T.W and Nasif",
    "rom_support": "https://t.me/ancientid",
    "device_supportgp_url": "https://t.me/ancient_Realme3",
    "changelog_url": "https://t.me/ancientrom/1392",
    "date_updated": "18-01-2022",
    "download_url": "https://www.pling.com/p/1606752",
    "phone_url": "https://fdn2.gsmarena.com/vv/pics/realme/realme-3-1.jpg"
  },
  {
    "device_codename": "Realme X2",
    "maintainer": "CHAITANYA",
    "rom_support": "https://t.me/ancientid",
    "device_supportgp_url": "https://t.me/ancientofficial_X2",
    "changelog_url": "https://t.me/ancientrom/1392",
    "date_updated": "9-1-2022",
    "download_url": "https://www.pling.com/p/1606752",
    "phone_url": "https://fdn2.gsmarena.com/vv/pics/realme/realme-xt-730g.jpg"
  },
  {
    "device_codename": "Redmi Note 7",
    "maintainer": "ABRAR",
    "rom_support": "https://t.me/ancientid",
    "device_supportgp_url": "https://t.me/ancientofficiallavender",
    "changelog_url": "https://telegra.ph/AncientOS-62-01-27",
    "date_updated": "27-01-2022",
    "download_url": "https://www.pling.com/p/1606752",
    "phone_url": "https://i01.appmifile.com/v1/MI_18455B3E4DA706226CF7535A58E875F0267/pms_1551087520.34558030.jpg%20%22Xiaomi%20Redmi%20Note%207%20Pro%20in%20Neptune%20Blue%22"
   },
   {
    "device_codename": "Redmi 4X",
    "maintainer": "Krxyzn",
    "rom_support": "https://t.me/ancientid",
    "device_supportgp_url": "https://t.me/AncentSantoni",
    "changelog_url": "https://t.me/ancientrom/1392",
    "date_updated": "25-12-2021",
    "download_url": "https://www.pling.com/p/1606752",
    "phone_url": "https://cdn.tgdd.vn/Products/Images/42/99145/xiaomi-redmi-4x-400-400x460.png"
    },
   {
    "device_codename": "Redmi 7/Y3 (onclite/onc)",
    "maintainer": "𝘗𝘦𝘯𝘦𝘵𝘳𝘢𝘵𝘰𝘙",
    "rom_support": "https://t.me/ancientid",
    "device_supportgp_url": "https://t.me/Predators_Abode",
    "changelog_url": "https://t.me/ancientrom/1392",
    "date_updated": "29-12-2021",
    "download_url": "https://www.pling.com/p/1606752",
    "phone_url": "https://telegra.ph/file/856849d62c30dc3a2679a.png"
   },
   {
    "device_codename": "Redmi 9T / Redmi 9 Power / Redmi Note 9 4G and POCO M3 (Juice)",
    "maintainer": "Indra DP and Vern Kuato",
    "rom_support": "https://t.me/ancientid",
    "device_supportgp_url": "https://t.me/ancientosjuice",
    "changelog_url": "https://t.me/ancientrom/1392",
    "date_updated": "19-12-2021",
    "download_url": "https://www.pling.com/p/1606752",
    "phone_url": "https://blogger.googleusercontent.com/img/a/AVvXsEjoDAUaBMZFeqK5qfBmOJq9qit-2FbnruxYoZFnp8GxzpngFQO1QrfUJfoz34CPwWS3KFgNDiUlR5H_E6GZFXV6YMq0kMGZM5wfeZATW_R7ITRbvkrWZONzip2IDjMAq33xCNF1USfLX_6Qek24fcT6_gLE5Kz-K1BmvFyEt3QEpljMx2DHlLmPDbAg"
   },
   {
    "device_codename": "Redmi Note 10 Pro (Sweet)",
    "maintainer": "BMW",
    "rom_support": "https://t.me/ancientid",
    "device_supportgp_url": "[BMW](https://t.me/bmwtheseries)",
    "changelog_url": "https://t.me/ancientrom/1394",
    "date_updated": "07-01-2022",
    "download_url": "https://www.pling.com/p/1606752",
    "phone_url": "https://fdn2.gsmarena.com/vv/bigpic/xiaomi-redmi-note10-pro.jpg"
   },
   {
    "device_codename": "realme RM6785 (realme 6/6i(Indian)/6s/7/Narzo/narzo 20 Pro/narzo 30 4G)",
    "maintainer": "A Zaidan",
    "rom_support": "https://t.me/ancientid",
    "device_supportgp_url": "https://t.me/ancientRM6785",
    "changelog_url": "https://t.me/ancientrom/1392",
    "date_updated": "22-12-2021",
    "download_url": "https://www.pling.com/p/1606752",
    "phone_url": "https://raw.githubusercontent.com/ancient-devices/ancient_official_devices/main/RMX2151.png"
   },
   {
    "device_codename": "POCO F3 / Redmi K40 / Mi 11x (alioth/aliothin)",
    "maintainer": "oghe3003 and Eduardo",
    "rom_support": "https://t.me/ancientid",
    "device_supportgp_url": "https://t.me/ancientofficialalioth",
    "changelog_url": "https://t.me/ancientrom/1392",
    "date_updated": "25-01-2022",
    "download_url": "https://www.pling.com/p/1606752",
    "phone_url": "https://raw.githubusercontent.com/oghe3003/official_device_xiaomi/main/alioth.png"
   },
   {
    "device_codename": "Mi 11 Lite (courbet/courbetin)",
    "maintainer": "ygherna",
    "rom_support": "https://t.me/ancientcourbet",
    "device_supportgp_url": "https://t.me/mi11litechat",
    "changelog_url": "https://t.me/ancientrom/1392",
    "date_updated": "24-01-2022",
    "download_url": "https://www.pling.com/p/1606752",
    "phone_url": "https://fdn2.gsmarena.com/vv/pics/xiaomi/xiaomi-mi-11-lite-4g-1.jpg"
   },
   {
    "device_codename": "Redmi 4A/5A",
    "maintainer": "Ridwan Adi Cahyono (ItoRenz)",
    "rom_support": "https://t.me/ancientid",
    "device_supportgp_url": "https://t.me/ancientofficialrova",
    "changelog_url": "https://t.me/ancientrom/1392",
    "date_updated": "20-12-2021",
    "download_url": "https://www.pling.com/p/1606752",
    "phone_url": "https://telegra.ph/file/0a82564e7bb6712b182d5.jpg"
   },
   {
    "device_codename": "Redmi 5 Plus",
    "maintainer": "Edwiin Kusuma Jaya (Ryuzenn)",
    "rom_support": "https://t.me/ancientid",
    "device_supportgp_url": "https://t.me/ancientofficialvince",
    "changelog_url": "https://t.me/ancientrom/1392",
    "date_updated": "24-12-2021",
    "download_url": "https://www.pling.com/p/1606752",
    "phone_url": "https://raw.githubusercontent.com/kutemeikito/Ryzen-Script/master/vince.png"
   },
   {
    "device_codename": "Realme 6 Pro",
    "maintainer": "NEMESIS",
    "rom_support": "https://t.me/ancientid",
    "device_supportgp_url": "https://t.me/ancientOSofficialRMX2061",
    "changelog_url": "https://t.me/ancientrom/1392",
    "date_updated": "28-01-2022",
    "download_url": "https://www.pling.com/p/1606752",
    "phone_url": "https://telegra.ph/file/f7feada16214cb2189338.jpg"
   },
   {
    "device_codename": "Redmi Note 9S, Redmi Note 9 Pro India, Redmi Note 10 Lite, Redmi Note 9 Pro Global, Redmi Note 9 Pro Max India, POCO M2 Pro",
    "maintainer": "ThisIsTag",
    "rom_support": "https://t.me/ancientid",
    "device_supportgp_url": "https://t.me/ThisIsGroup2",
    "changelog_url": "https://t.me/ancientrom/1392",
    "date_updated": "29-12-2021",
    "download_url": "https://www.pling.com/p/1606752",
    "phone_url": "https://upload.wikimedia.org/wikipedia/commons/thumb/e/ea/Redmi_note_9s_.webp/640px-Redmi_note_9s_.webp.png"
   },
   {
    "device_codename": "Redmi Note 5 Pro(Whyred)",
    "maintainer": "Adrar Hussain",
    "rom_support": "https://t.me/ancientid",
    "device_supportgp_url": "https://t.me/ancientofficialwhyred",
    "changelog_url": "https://t.me/ancientrom/1392",
    "date_updated": "29-12-2021",
    "download_url": "https://www.pling.com/p/1606752",
    "phone_url": "https://telegra.ph/file/d44358afe0fe98893c1f7.png"
   },
   {
    "device_codename": "Redmi Note 8/8T (Ginkgo/Willow)",
    "maintainer": "Ryuzenn && Erwin ABS",
    "rom_support": "https://t.me/ancientid",
    "device_supportgp_url": "https://t.me/ancientofficialginkgo",
    "changelog_url": "https://t.me/ancientrom/1392",
    "date_updated": "30-12-2021",
    "download_url": "https://www.pling.com/p/1606752",
    "phone_url": "https://raw.githubusercontent.com/kutemeikito/Ryzen-Script/master/ginkgo.png"
   },
   {
    "device_codename": "Xiaomi MI A3 (laurel_sprout)",
    "maintainer": "Magicxavi",
    "rom_support": "https://t.me/ancientid",
    "device_supportgp_url": "https://t.me/ancient_official_laurel",
    "changelog_url": "https://t.me/ancientrom/1392",
    "date_updated": "31-12-2021",
    "download_url": "https://www.pling.com/p/1606752",
    "phone_url": "http://i01.appmifile.com/webfile/globalimg/products/pc/mi-a3/specs2.png"
   },
   {
    "device_codename": "Redmi 9C / 9C NFC / 9A / 9 India / POCO C3 (garden)",
    "maintainer": "Mikazuuu07",
    "rom_support": "https://t.me/ancientid",
    "device_supportgp_url": "https://t.me/AncientGarden",
    "changelog_url": "https://t.me/ancientrom/1392",
    "date_updated": "17-01-2022",
    "download_url": "https://www.pling.com/p/1606752",
    "phone_url": "https://fdn2.gsmarena.com/vv/pics/xiaomi/xiaomi-redmi-9c-nfc.jpg"
   },
   {
    "device_codename": "OnePlus Nord 2 5G (denniz)",
    "maintainer": "hypercleric",
    "rom_support": "https://t.me/ancientid",
    "device_supportgp_url": "https://t.me/ancientDenniz",
    "changelog_url": "https://t.me/ancientrom/1392",
    "date_updated": "12-01-2022",
    "download_url": "https://www.pling.com/p/1606752",
    "phone_url": "https://fdn2.gsmarena.com/vv/pics/oneplus/oneplus-nord-2-5g-1.jpg"
   },
   {
    "device_codename": "Samsung Galaxy A10 (a10)",
    "maintainer": "Gabriel260",
    "rom_support": "https://t.me/ancientid",
    "device_supportgp_url": "https://t.me/ancient_a10",
    "changelog_url": "https://t.me/ancientrom/1392",
    "date_updated": "12-01-2022",
    "download_url": "https://www.pling.com/p/1606752",
    "phone_url": "https://fdn2.gsmarena.com/vv/pics/samsung/samsung-galaxy-a10-0.jpg"
   },
   {
    "device_codename": "Redmi Note 9 (merlinx)",
    "maintainer": "Mikazuuu07",
    "rom_support": "https://t.me/ancientid",
    "device_supportgp_url": "https://t.me/ancientosmerlinx",
    "changelog_url": "https://t.me/ancientrom/1392",
    "date_updated": "16-01-2022",
    "download_url": "https://www.pling.com/p/1606752",
    "phone_url": "https://fdn2.gsmarena.com/vv/pics/xiaomi/xiaomi-redmi-note-9-4.jpg"
   },
   {
    "device_codename": "Redmi Note 10 (mojito)",
    "maintainer": "ArhamDharewa",
    "rom_support": "https://t.me/ancientid",
    "device_supportgp_url": "https://t.me/ancientofficialmojito",
    "changelog_url": "https://www.ancientrom.tech/",
    "date_updated": "27-01-2022",
    "download_url": "https://www.pling.com/p/1606752",
    "phone_url": "https://telegra.ph/file/2de89d1f6dce1118024ed.jpg"
   },
   {
    "device_codename": "Redmi Note 9 Pro 5G / Mi 10T Lite / Mi 10i (gauguin)",
    "maintainer": "Huha Lula",
    "rom_support": "https://t.me/ancientid",
    "device_supportgp_url": "https://t.me/ancient_gauguin",
    "changelog_url": "https://t.me/ancientrom/1393",
    "date_updated": "19-01-2022",
    "download_url": "https://www.pling.com/p/1606752",
    "phone_url": "https://fdn2.gsmarena.com/vv/bigpic/xiaomi-mi-10i-5g.jpg"
   },
   {
    "device_codename": "Realme X7 Max 5G (RMX3031)",
    "maintainer": "NishantKumar6342",
    "rom_support": "https://t.me/ancientid",
    "device_supportgp_url": "https://t.me/ancientRMX3031",
    "changelog_url": "https://t.me/ancientrom/1392",
    "date_updated": "21-01-2022",
    "download_url": "https://www.pling.com/p/1606752",
    "phone_url": "https://fdn2.gsmarena.com/vv/bigpic/realme-x7-max-5g.jpg"
   },
   {
    "device_codename": "Poco X3 Pro (vayu)",
    "maintainer": "Alisson Grizotti",
    "rom_support": "https://t.me/ancientid",
    "device_supportgp_url": "https://t.me/ancientvayu",
    "changelog_url": "https://t.me/ancientrom/1392",
    "date_updated": "25-01-2022",
    "download_url": "https://www.pling.com/p/1606752",
    "phone_url": "https://files.tecnoblog.net/wp-content/uploads/2021/08/poco-x3-pro-produto-700x700.png"
   }
]
